nameko_chassis/__init__.py
nameko_chassis/containers.py
nameko_chassis/debug.py
nameko_chassis/dependencies.py
nameko_chassis/discovery.py
nameko_chassis/health.py
nameko_chassis/py.typed
nameko_chassis/service.py
nameko_chassis-3.2.0.dist-info/WHEEL
nameko_chassis-3.2.0.dist-info/METADATA
nameko_chassis-3.2.0.dist-info/RECORD
