Metadata-Version: 2.3
Name: nameko-chassis
Version: 3.2.0
Summary: nameko-chassis provides an opinionated base class for building resilient, observable microservices.
Author: Emplocity
License: Apache Software License 2.0
Classifier: Development Status :: 3 - Alpha
Classifier: Intended Audience :: Developers
Classifier: License :: OSI Approved :: Apache Software License
Classifier: Operating System :: Unix
Classifier: Operating System :: POSIX
Classifier: Programming Language :: Python
Classifier: Programming Language :: Python :: 3
Classifier: Programming Language :: Python :: 3.10
Classifier: Programming Language :: Python :: 3.11
Classifier: Programming Language :: Python :: 3.12
Classifier: Programming Language :: Python :: 3.13
Classifier: Programming Language :: Python :: 3.14
Classifier: Programming Language :: Python :: Implementation :: CPython
Classifier: Topic :: Utilities
Requires-Dist: nameko>=3.0rc11
Requires-Dist: nameko-prometheus>=1.5.0
Requires-Dist: opentelemetry-api>=1.14
Requires-Dist: opentelemetry-distro>=0.35b0
Requires-Dist: opentelemetry-exporter-otlp-proto-http>=1.14
Requires-Dist: opentelemetry-instrumentation-nameko>=0.5
Requires-Dist: opentelemetry-sdk>=1.14
Requires-Dist: opentelemetry-instrumentation-logging>=0.35b0
Requires-Dist: pyrabbit>=1.1
Requires-Dist: sentry-sdk>=2
Requires-Dist: werkzeug>=2.0
Requires-Python: >=3.10
Project-URL: Changelog, https://nameko-chassis.readthedocs.io/en/latest/changelog.html
Project-URL: Documentation, https://nameko-chassis.readthedocs.io/
Project-URL: Homepage, https://github.com/Emplocity/nameko-chassis
Project-URL: Issue Tracker, https://github.com/Emplocity/nameko-chassis/issues
